main.py
simple_backup-0.1.8.dist-info/METADATA
simple_backup-0.1.8.dist-info/WHEEL
simple_backup-0.1.8.dist-info/entry_points.txt
simple_backup-0.1.8.dist-info/top_level.txt
simple_backup-0.1.8.dist-info/RECORD
