Metadata-Version: 2.4
Name: simple-backup
Version: 0.1.8
Summary: Простой инструмент для создания и восстановления бэкапов проектов в YAML формате
Author-email: vpuhoff <vpuhoff92@gmail.com>
Project-URL: Homepage, https://github.com/vpuhoff/simple-backup-tool
Project-URL: Repository, https://github.com/vpuhoff/simple-backup-tool
Keywords: backup,yaml,project,restore,cli
Classifier: Development Status :: 4 - Beta
Classifier: Intended Audience :: Developers
Classifier: License :: OSI Approved :: MIT License
Classifier: Programming Language :: Python :: 3
Classifier: Programming Language :: Python :: 3.9
Classifier: Programming Language :: Python :: 3.10
Classifier: Programming Language :: Python :: 3.11
Classifier: Programming Language :: Python :: 3.12
Classifier: Topic :: System :: Archiving :: Backup
Classifier: Topic :: Utilities
Requires-Python: >=3.9
Requires-Dist: pyyaml>=6.0
Requires-Dist: click>=8.0
Provides-Extra: dev
Requires-Dist: pytest>=7.0; extra == "dev"
Requires-Dist: pytest-cov>=4.0; extra == "dev"
Requires-Dist: flake8>=6.0; extra == "dev"
Requires-Dist: mypy>=1.0; extra == "dev"
